pyfcstm/__init__.py
pyfcstm/__main__.py
pyfcstm/config/__init__.py
pyfcstm/config/meta.py
pyfcstm/dsl/__init__.py
pyfcstm/dsl/error.py
pyfcstm/dsl/listener.py
pyfcstm/dsl/node.py
pyfcstm/dsl/parse.py
pyfcstm/dsl/grammar/Grammar.g4
pyfcstm/dsl/grammar/Grammar.interp
pyfcstm/dsl/grammar/Grammar.tokens
pyfcstm/dsl/grammar/GrammarLexer.interp
pyfcstm/dsl/grammar/GrammarLexer.py
pyfcstm/dsl/grammar/GrammarLexer.tokens
pyfcstm/dsl/grammar/GrammarListener.py
pyfcstm/dsl/grammar/GrammarParser.py
pyfcstm/dsl/grammar/__init__.py
pyfcstm/entry/__init__.py
pyfcstm/entry/base.py
pyfcstm/entry/cli.py
pyfcstm/entry/dispatch.py
pyfcstm/entry/generate.py
pyfcstm/entry/plantuml.py
pyfcstm/model/__init__.py
pyfcstm/model/base.py
pyfcstm/model/expr.py
pyfcstm/model/model.py
pyfcstm/render/__init__.py
pyfcstm/render/env.py
pyfcstm/render/expr.py
pyfcstm/render/func.py
pyfcstm/render/render.py
pyfcstm/utils/__init__.py
pyfcstm/utils/binary.py
pyfcstm/utils/decode.py
pyfcstm/utils/doc.py
pyfcstm/utils/jinja2.py
pyfcstm/utils/json.py
pyfcstm/utils/safe.py
pyfcstm/utils/text.py
pyfcstm/utils/validate.py
pyfcstm-0.2.1.dist-info/LICENSE
pyfcstm-0.2.1.dist-info/METADATA
pyfcstm-0.2.1.dist-info/WHEEL
pyfcstm-0.2.1.dist-info/entry_points.txt
pyfcstm-0.2.1.dist-info/top_level.txt
pyfcstm-0.2.1.dist-info/RECORD
