Metadata-Version: 2.1
Name: pyfcstm
Version: 0.2.1
Summary: A Python framework for parsing finite state machine DSL and generating executable code in multiple target languages.
Home-page: https://github.com/hansbug/pyfcstm
Author: HansBug
Author-email: hansbug@buaa.edu.cn
License: GNU Lesser General Public License v3 (LGPLv3)
Project-URL: Homepage, https://github.com/hansbug/pyfcstm
Project-URL: Documentation, https://pyfcstm.readthedocs.io/
Project-URL: Source, https://github.com/hansbug/pyfcstm
Project-URL: Download, https://pypi.org/project/pyfcstm/#files
Project-URL: Bug Reports, https://github.com/hansbug/pyfcstm/issues
Project-URL: Contributing, https://github.com/hansbug/pyfcstm/blob/main/CONTRIBUTING.md
Project-URL: Pull Requests, https://github.com/hansbug/pyfcstm/pulls
Project-URL: CI, https://github.com/hansbug/pyfcstm/actions
Project-URL: Coverage, https://codecov.io/gh/hansbug/pyfcstm
Project-URL: Wiki, https://github.com/hansbug/pyfcstm/wiki
Project-URL: License, https://github.com/hansbug/pyfcstm/blob/main/LICENSE
Keywords: state-machine,code-generation,compiler,template-engine,modelling
Classifier: Development Status :: 5 - Production/Stable
Classifier: Intended Audience :: Developers
Classifier: Intended Audience :: Science/Research
Classifier: Intended Audience :: Information Technology
Classifier: Intended Audience :: Manufacturing
Classifier: Intended Audience :: System Administrators
Classifier: License :: OSI Approved :: GNU Lesser General Public License v3 (LGPLv3)
Classifier: Programming Language :: Python
Classifier: Programming Language :: Python :: 3
Classifier: Programming Language :: Python :: 3 :: Only
Classifier: Programming Language :: Python :: 3.8
Classifier: Programming Language :: Python :: 3.9
Classifier: Programming Language :: Python :: 3.10
Classifier: Programming Language :: Python :: 3.11
Classifier: Programming Language :: Python :: 3.12
Classifier: Programming Language :: Python :: 3.13
Classifier: Operating System :: OS Independent
Classifier: Operating System :: POSIX
Classifier: Operating System :: Microsoft :: Windows
Classifier: Operating System :: MacOS
Classifier: Topic :: Scientific/Engineering
Classifier: Topic :: Scientific/Engineering :: Mathematics
Classifier: Topic :: Scientific/Engineering :: Visualization
Classifier: Topic :: Software Development
Classifier: Topic :: Software Development :: Libraries
Classifier: Topic :: Software Development :: Libraries :: Python Modules
Classifier: Topic :: Software Development :: Code Generators
Classifier: Topic :: Software Development :: Compilers
Classifier: Topic :: Software Development :: Interpreters
Classifier: Topic :: Software Development :: Pre-processors
Classifier: Topic :: Software Development :: Build Tools
Classifier: Topic :: Text Processing
Classifier: Topic :: Text Processing :: Linguistic
Classifier: Topic :: Text Processing :: Markup
Classifier: Topic :: System :: Systems Administration
Classifier: Topic :: System :: Monitoring
Classifier: Topic :: Utilities
Classifier: Topic :: Documentation
Classifier: Typing :: Typed
Classifier: Natural Language :: English
Requires-Python: >=3.7
License-File: LICENSE
Requires-Dist: hbutils
Requires-Dist: natsort
Requires-Dist: cachetools
Requires-Dist: pyyaml
Requires-Dist: antlr4-python3-runtime ==4.9.3
Requires-Dist: jinja2 >=3
Requires-Dist: unidecode
Requires-Dist: pathspec
Requires-Dist: click >=8
Requires-Dist: chardet
Provides-Extra: build
Requires-Dist: pyinstaller >=4.7 ; extra == 'build'
Requires-Dist: setuptools ; extra == 'build'
Requires-Dist: hbutils ; extra == 'build'
Provides-Extra: dev
Requires-Dist: ruff ; extra == 'dev'
Requires-Dist: antlr4-python3-runtime ==4.9.3 ; extra == 'dev'
Provides-Extra: doc
Requires-Dist: Jinja2 >=3.0.0 ; extra == 'doc'
Requires-Dist: sphinx >=3.2.0 ; extra == 'doc'
Requires-Dist: sphinx-rtd-theme >=0.4.3 ; extra == 'doc'
Requires-Dist: enum-tools >=0.9.0 ; extra == 'doc'
Requires-Dist: sphinx-toolbox ; extra == 'doc'
Requires-Dist: plantumlcli >=0.0.2 ; extra == 'doc'
Requires-Dist: packaging ; extra == 'doc'
Requires-Dist: sphinx-multiversion >=0.2.4 ; extra == 'doc'
Requires-Dist: where >=1.0.2 ; extra == 'doc'
Requires-Dist: easydict <2,>=1.7 ; extra == 'doc'
Requires-Dist: responses >=0.20.0 ; extra == 'doc'
Requires-Dist: natsort ; extra == 'doc'
Requires-Dist: nbsphinx >=0.8.8 ; extra == 'doc'
Requires-Dist: ipython >=7.16.3 ; extra == 'doc'
Requires-Dist: psutil >=5.8.0 ; extra == 'doc'
Requires-Dist: ipykernel >=6.15 ; extra == 'doc'
Requires-Dist: py-cpuinfo >=8.0.0 ; extra == 'doc'
Requires-Dist: click >=7.0.0 ; extra == 'doc'
Requires-Dist: pandas ; extra == 'doc'
Requires-Dist: sphinxcontrib-svg2pdfconverter ; extra == 'doc'
Provides-Extra: test
Requires-Dist: coverage >=5 ; extra == 'test'
Requires-Dist: mock >=4.0.3 ; extra == 'test'
Requires-Dist: flake8 >=3.5 ; extra == 'test'
Requires-Dist: testfixtures >=6.18.5 ; extra == 'test'
Requires-Dist: pytest >=6.2.5 ; extra == 'test'
Requires-Dist: pytest-cov >=3.0.0 ; extra == 'test'
Requires-Dist: pytest-mock >=3.6.1 ; extra == 'test'
Requires-Dist: pytest-xdist >=1.34.0 ; extra == 'test'
Requires-Dist: pytest-rerunfailures >=10.2 ; extra == 'test'
Requires-Dist: pytest-timeout >=2.0.2 ; extra == 'test'
Requires-Dist: pytest-benchmark >=3.4.0 ; extra == 'test'
Requires-Dist: easydict <2,>=1.7 ; extra == 'test'
Requires-Dist: testtools >=2 ; extra == 'test'
Requires-Dist: where >=1.0.2 ; extra == 'test'
Requires-Dist: natsort ; extra == 'test'
